rmlab/__init__.py
rmlab/_version.py
rmlab/_api/__init__.py
rmlab/_api/base.py
rmlab/_api/fetch.py
rmlab/_api/observability.py
rmlab/_api/remove.py
rmlab/_api/simulation.py
rmlab/_api/upload.py
rmlab/_data/__init__.py
rmlab/_data/conversions.py
rmlab/_data/enums.py
rmlab/_data/types.py
rmlab/_util/__init__.py
rmlab/api/__init__.py
rmlab/api/remove.py
rmlab/api/fetch/__init__.py
rmlab/api/fetch/core.py
rmlab/api/fetch/flight_data.py
rmlab/api/fetch/parametric.py
rmlab/api/observability/__init__.py
rmlab/api/operations/__init__.py
rmlab/api/operations/optimization.py
rmlab/api/operations/simulation.py
rmlab/api/persistence/__init__.py
rmlab/api/upload/__init__.py
rmlab/api/upload/core.py
rmlab/api/upload/flight_data.py
rmlab/api/upload/parametric/__init__.py
rmlab/api/upload/parametric/customers.py
rmlab/api/upload/parametric/filters.py
rmlab/api/upload/parametric/pricing.py
rmlab/data/__init__.py
rmlab/data/flight.py
rmlab/data/items.py
rmlab/data/scenario.py
rmlab/data/parametric/__init__.py
rmlab/data/parametric/_customers_base.py
rmlab/data/parametric/_pricing_base.py
rmlab/data/parametric/customers_choice.py
rmlab/data/parametric/customers_request.py
rmlab/data/parametric/filter.py
rmlab/data/parametric/pricing_behavior.py
rmlab/data/parametric/pricing_optimizer.py
rmlab/data/parametric/pricing_range.py
rmlab-0.4.4.dist-info/LICENSE
rmlab-0.4.4.dist-info/METADATA
rmlab-0.4.4.dist-info/WHEEL
rmlab-0.4.4.dist-info/top_level.txt
rmlab-0.4.4.dist-info/RECORD
