Metadata-Version: 2.1
Name: rmlab
Version: 0.4.4
Summary: RMLab python client
Home-page: https://rmlab.ai
Author: Anton Rey
Author-email: aanton.rv@gmail.com
Project-URL: Bug Tracker, https://rmlab.ai
Classifier: License :: OSI Approved :: MIT License
Classifier: Development Status :: 4 - Beta
Classifier: Programming Language :: Python
Classifier: Programming Language :: Python :: 3.11
Classifier: Programming Language :: Python :: 3 :: Only
Classifier: Operating System :: OS Independent
Classifier: Environment :: Console
Classifier: Intended Audience :: Developers
Classifier: Topic :: Office/Business
Classifier: Topic :: Scientific/Engineering
Classifier: Topic :: Software Development :: User Interfaces
Classifier: Framework :: AsyncIO
Requires-Python: >=3.11
License-File: LICENSE
Requires-Dist: rmlab-http-client (==0.4.0)
Requires-Dist: tqdm (==4.63.0)
